py_cron_schedule/__init__.py
py_cron_schedule/cron_schedule.py
py_cron_schedule-0.0.7.dist-info/LICENSE
py_cron_schedule-0.0.7.dist-info/LICENSE_996
py_cron_schedule-0.0.7.dist-info/METADATA
py_cron_schedule-0.0.7.dist-info/WHEEL
py_cron_schedule-0.0.7.dist-info/top_level.txt
py_cron_schedule-0.0.7.dist-info/RECORD
