Metadata-Version: 2.1
Name: py-cron-schedule
Version: 0.0.7
Summary: Python Crontab Syntax Scheduler.
Home-page: https://github.com/Thoxvi/PyCronSchedule
Author: Thoxvi
Author-email: A@Thoxvi.com
License: UNKNOWN
Keywords: crontab schedule scheduler
Platform: UNKNOWN
Classifier: Programming Language :: Python
Classifier: Programming Language :: Python :: Implementation
Classifier: Programming Language :: Python :: 3.4
Classifier: Programming Language :: Python :: 3.5
Classifier: Programming Language :: Python :: 3.6
Classifier: Topic :: Software Development :: Libraries
Requires-Python: >=3.4
